{
  "meta": {
    "version": "1.0.0-beta2",
    "category": "source",
    "defaultLanguage": "en",
    "dateCreated": "2022-03-24T00:00:00+00:00"
  },
  "idAuthorities": {},
  "identification": {
    "primary": {
      "xyz": {}
    },
    "name": {
      "en": "minimal source scripture textTranslation-flavored burrito"
    }
  },
  "confidential": false,
  "copyright": {
    "publicDomain": true
  },
  "type": {
    "flavorType": {
      "name": "scripture",
      "flavor": {
        "name": "textTranslation",
        "projectType": "standard",
        "translationType": "newTranslation",
        "audience": "common",
        "usfmVersion": "3.0"
      },
      "currentScope": {
        "1JN": []
      }
    }
  },
  "languages": [
    {
      "tag": "en",
      "name": {
        "en": "English"
      }
    }
  ],
  "ingredients": {
    "text.txt": {
      "size": 10,
      "mimeType": "text/plain"
    }
  }
}
